README.rst
setup.py
tests/__init__.py
tests/test_core.py
tests/test_parsers.py
torefl/__init__.py
torefl/__main__.py
torefl/config.py
torefl/core.py
torefl/filter.py
torefl/legacyFilter.py
torefl/parser.py
torefl/shell.py
torefl.egg-info/PKG-INFO
torefl.egg-info/SOURCES.txt
torefl.egg-info/dependency_links.txt
torefl.egg-info/entry_points.txt
torefl.egg-info/not-zip-safe
torefl.egg-info/requires.txt
torefl.egg-info/top_level.txt
torefl/exporters/BibtexExporter.py
torefl/exporters/__init__.py
torefl/formatters/ASCIIFormatter.py
torefl/formatters/__init__.py