Metadata-Version: 1.1
Name: torefl
Version: 1.0b4
Summary: Software to manage references
Home-page: https://github.com/hl037/torefl
Author: hl037
Author-email: hl037.prog@gmail.com
License: GPL
Keywords: torefl,bibtex,bibliography,reference,pdf,management
Platform: UNKNOWN
Classifier: Development Status :: 4 - Beta
Classifier: Environment :: Console
Classifier: Intended Audience :: Developers
Classifier: Intended Audience :: Education
Classifier: Intended Audience :: Science/Research
Classifier: License :: OSI Approved :: GNU General Public License v3 (GPLv3)
Classifier: Natural Language :: English
Classifier: Operating System :: OS Independent
Classifier: Programming Language :: Python :: 3
Classifier: Topic :: Scientific/Engineering
Classifier: Topic :: Utilities
Classifier: Topic :: Other/Nonlisted Topic
